Workbook

Sheet summary
K2: fuel station in 2017 :
A4: SN | B4: Date | C4: Bank | D4: fuel stations | E4: Description | K4: collection | L4: loaded | M4: difference
D5: Gesuba(Welaita) | I5: ='Gesuba(Welaita)'!K72 -> 52276377 | K5: ='Gesuba(Welaita)'!K46 -> 58777482 | L5: ='Gesuba(Welaita)'!K72 -> 52276377 | M5: =K5-L5 -> 6501104.6
D6: metu(Elibabora) | K6: ='Metu(Elibabora)'!K51 -> 60645926 | L6: ='Metu(Elibabora)'!K78 -> 54094781 | M6: =K6-L6 -> 6551145.4
D7: Leha(Gofa) | K7: ='Leha(Gofa)'!K51 -> 45813228 | L7: ='Leha(Gofa)'!K86 -> 33056293 | M7: =K7-L7 -> 12756935
D8: Mito(Silta) | K8: ='Mito(Silta)'!K51 -> 35921855 | L8: ='Mito(Silta)'!K86 -> 31502508 | M8: =K8-L8 -> 4419346.7
D9: Batu(Coustic) | K9: ='Batu(Coustic Soda)'!K51 -> 12238955 | L9: ='Batu(Coustic Soda)'!K86 -> 11814647 | M9: =K9-L9 -> 424307.49
D10: DashenGonder) | K10: ='Dashine(Gonder)'!K51 -> 34795274 | L10: ='Dashine(Gonder)'!K86 -> 26876010 | M10: =K10-L10 -> 7919264.6
D11: Dubti(Sordo) | K11: ='Dubti(Sordo)'!K47 -> 1400000 | L11: ='Dubti(Sordo)'!K85 -> 3722989.5 | M11: =K11-L11 -> -2322989.5
D12: S.Humera | K12: =S.Humera!K47 -> 7000000 | L12: =S.Humera!K85 -> 8574100.2 | M12: =K12-L12 -> -1574100.2
D13: Adebay | K13: =Adebay!K50 -> 8400000 | L13: =Adebay!K84 -> 8788545.2 | M13: =K13-L13 -> -388545.25
D14: Baeker | K14: =Baeker!K50 -> 25300000 | L14: =Baeker!K85 -> 20055678 | M14: =K14-L14 -> 5244321.9
D15: Dansha(Wendem) | K15: ='Dansha(Wendem)'!L47 -> 17821732 | L15: ='Dansha(Wendem)'!L86 -> 17294642 | M15: =K15-L15 -> 527089.99
D16: Gonder Bikl Factory | K16: ='Gonder Bikl Factory'!K50 -> 4281600 | L16: ='Gonder Bikl Factory'!K85 -> 3431987.8 | M16: =K16-L16 -> 849612.16
D17: total | K17: =SUM(K5:K16) -> 3.1239605e+08 | L17: =SUM(L5:L16) -> 2.7148856e+08 | M17: =SUM(M5:M16) -> 40907493

Sheet EpSE Report
D2: EPSE Balance Report | J2: Date | K2: 45481
A4: SN | B4: Date | C4: Bank | D4: Reference | E4: Receit No | F4: Description | K4: Amounts
D5: Transfer from last Year | K5: 7806062.2
E6: Advance paid to EPSE :
A7: 1 | B7: 10/07/24 | C7: CBE | E7: Advance paid to EPSE : | K7: 4000000
A8: 2 | B8: 10/07/24 | C8: CBE | E8: Advance paid to EPSE : | K8: 1000000
A9: 3 | B9: 45488 | C9: CBE | E9: Advance paid to EPSE : | K9: 500000
A10: 4 | B10: 45489 | C10: CBE | E10: Advance paid to EPSE : | K10: 500000
A11: 5 | B11: 45489 | C11: CBE | E11: Advance paid to EPSE : | K11: 2700000
A12: 6 | B12: 45490 | C12: CBE | E12: Advance paid to EPSE : | K12: 4500000
A13: 7 | B13: 45497 | C13: CBE | E13: Advance paid to EPSE : | K13: 2000000
A14: 8 | B14: 45497 | C14: Awash | E14: Advance paid to EPSE : | K14: 2000000
A15: 9 | B15: 45499 | C15: CBE | D15: FT242085B3FW | E15: Advance paid to EPSE : | K15: 4200000
A16: 10 | B16: 45499 | C16: CBE | D16: FT24208VYRZQ | E16: Advance paid to EPSE : | K16: 6000000
A17: 11 | B17: 45502 | C17: CBE | D17: FT24211QLPQR | E17: Advance paid to EPSE : | K17: 3200000
A18: 12 | B18: 45505 | C18: Dashine | D18: 124FtRQ2421400WL | E18: Advance paid to EPSE : | K18: 4000000
A19: 13 | B19: 45506 | C19: Awash | D19: 013041164408600 | E19: Advance paid to EPSE : | K19: 1400000
A20: 14 | B20: 45510 | C20: CBE | E20: Advance paid to EPSE : | K20: 2700000
A21: 15 | B21: 45511 | C21: CBE | E21: Advance paid to EPSE : | K21: 700000
A22: 16 | B22: 45513 | C22: CBE | D22: FT24222V3ZDQ | E22: Advance paid to EPSE : | K22: 3000000
A23: 17 | B23: 45513 | C23: CBE | D23: FT24222RF59F | E23: Advance paid to EPSE : | K23: 3500000
A24: 18 | B24: 45516 | C24: CBE | D24: FT242256N49B | E24: Advance paid to EPSE : | K24: 4000000
A25: 19 | B25: 45517 | C25: CBE | D25: FT24226D5254 | E25: Advance paid to EPSE : | K25: 2150000
A26: 20 | B26: 45517 | C26: Abysinya | D26: FT24226P0LHP | E26: Advance paid to EPSE : | K26: 850000
A27: 21 | B27: 45520 | C27: Dashen | D27: (mito) | E27: Advance paid to EPSE : | K27: 2000000
A28: 22 | B28: 45523 | C28: CBE | D28: FT24232YJ8MW | E28: Advance paid to EPSE : | K28: 4000000
A29: 23 | B29: 45523 | C29: Dashen | D29: 124FTRQ2423200WR | E29: Advance paid to EPSE : | K29: 2000000
A30: 24 | B30: 45525 | C30: CBE | D30: FT24234TINJS | E30: Advance paid to EPSE : | K30: 2500000
A31: 25 | B31: 45525 | C31: Abysinya | D31: FT24234LWN5K | E31: Advance paid to EPSE : | K31: 600000
A32: 26 | B32: 45525 | C32: CBE | D32: (Gesuba/W | E32: Advance paid to EPSE : | K32: 500000
A33: 27 | B33: 45533 | C33: CBE | D33: FT24242RVKXY | E33: Advance paid to EPSE : | K33: 4000000
... A53: 47 | B53: 45569 | C53: Abysinya | D53: FT24278DJXFM | E53: Advance paid to EPSE : | K53: 10000000
A54: 48 | B54: 45574 | C54: Brhan | E54: Advance paid to EPSE : | K54: 1700000
A55: 49 | B55: 45574 | C55: Dashen | D55: 124FTRQ24283000K | E55: Advance paid to EPSE : | K55: 3900000
A56: 50 | B56: 45575 | C56: CBE | D56: FT24284SSNNX | E56: Advance paid to EPSE : | K56: 1200000
A57: 51 | B57: 45575 | C57: Abysinya | D57: FT24284MGDXK | E57: Advance paid to EPSE : | K57: 2700000
A58: 52 | B58: 45578 | C58: CBE | D58: FT24290T94S6 | E58: Advance paid to EPSE : | K58: 4400000
A59: 53 | B59: 45582 | C59: CBE | D59: FT24291M57Q3 | E59: Advance paid to EPSE : | K59: 4300000
A60: 54 | B60: 45586 | C60: Dashen | D60: 124FTRQ2429500WW | E60: Advance paid to EPSE : | K60: 1400000
A61: 55 | B61: 45586 | C61: CBE | D61: FT24295XJZ8K | E61: Advance paid to EPSE : | K61: 8900000
A62: 56 | B62: 45597 | C62: CBE | E62: Advance paid to EPSE : | K62: 3700000 | L62: Dansha(Wendem)
A63: 57 | B63: 45601 | C63: Abysinya | D63: FT24310NOJ9K | E63: Advance paid to EPSE : | K63: 5000000
A64: 58 | B64: 45602 | C64: Dashen | D64: 124FTRQ2431100WJ | E64: Advance paid to EPSE : | K64: 2500000
A65: 59 | B65: 45602 | C65: Abysinya | D65: FT24311XBZDB | E65: Advance paid to EPSE : | K65: 1500000
A66: 60 | B66: 45603 | C66: Abysinya | D66: FT24312/5QRGV | E66: Advance paid to EPSE : | K66: 2500000
A67: 61 | B67: 45604 | C67: CBE | D67: FT243130TQF7 | E67: Advance paid to EPSE : | K67: 7600000
A68: 62 | B68: 45604 | C68: Awash | D68: 013041164408600 | E68: Advance paid to EPSE : | K68: 1000000
A69: 63 | B69: 45608 | C69: Awash | D69: 106111211697191186117 | E69: Advance paid to EPSE : | K69: 1800000
A70: 64 | B70: 45611 | C70: CBE | D70: FT2432OR8TS8 | E70: Advance paid to EPSE : | K70: 4000000
A71: 65 | B71: 45614 | C71: Dashen | D71: 124FTRQ243230003 | E71: Advance paid to EPSE : | K71: 4300000
A72: 66 | B72: 45614 | C72: CBE | D72: FT24323288ZK | E72: Advance paid to EPSE : | K72: 2200000
A73: 67 | B73: 45614 | C73: Awash | D73: KOT/1031/2024 | E73: Advance paid to EPSE : | K73: 2100000
A74: 68 | B74: 45618 | C74: CBE | D74: FT24327M8D32 | E74: Advance paid to EPSE : | K74: 3000000
... A92: 86 | B92: 45658 | C92: CBE | D92: Ft250011Vc0Z | E92: Advance paid to EPSE : | K92: 2000000
A93: 87
A94: 88
A95: 89
A96: 90
A97: 1.Trip on going expected
A98: SN | B98: Total | K98: =SUM(K5:K97) -> 2.5553606e+08
E100: Fuel Costs -EPSE
A101: 2
A102: 3 | B102: FDC# | C102: Loading Date | E102: Truck/Semi Trailor Plate No | F102: Origin | G102: Destination | H102: Type of Product | I102: QTY at 20 F | J102: Fuel cost Per Litrs | K102: Total fuel Cost Amount (In Birr) (G= E*F)
A103: 4 | D103: Driver's Name
A104: 5 | B104: 789278 | C104: 45481 | D104: Destalem Abreha | E104: 3-71435/21297 | F104: Djb | G104: Mito(Silta) | H104: MGR | I104: 46483 | J104: 71.6167 | K104: =I104*J104 -> 3328959.1
A105: 6 | B105: 790007 | C105: 45482 | D105: Sintayehu Esheta | E105: 3-91450/27736 | F105: Djb | G105: Gesuba(Welaita | H105: MGR | I105: 47580 | J105: 71.6167 | K105: =I105*J105 -> 3407522.6
A106: 7 | B106: 790976 | C106: 45485 | D106: Musa Adem | E106: 3-94462/28942 | F106: Djb | G106: Mykadra | H106: AGO | I106: 45977 | J106: 76.5447 | K106: =I106*J106 -> 3519295.7
A107: 8 | B107: 791486 | C107: 45486 | D107: Hassen Mehamed | E107: 3-94456/28742 | F107: Djb | G107: Awash | H107: AGO | I107: 46047 | K107: =I107*J107 -> 0
A108: 9 | B108: 791850 | C108: 45486 | D108: Tsehaye G/medhn | E108: 3-93045/28723 | F108: Djb | G108: Awash | H108: AGO | I108: 45918 | K108: =I108*J108 -> 0
A109: 10 | B109: 791485 | C109: 45487 | D109: Tesfemariam Birhane | E109: 3-98387/29971 | F109: Djb | G109: Awash | H109: AGO | I109: 46792 | K109: =I109*J109 -> 0
A110: 11 | B110: 786564 | C110: 45487 | D110: Wedneh Bekele | E110: 3-93601/28714 | F110: Djb | G110: Batu(Coustc | H110: HFO | I110: 45946 | J110: 57.7473 | K110: =I110*J110 -> 2653257.4
A111: 12 | B111: 790976 | C111: 45493 | D111: Niguse Tadese | E111: 3-93449/28749 | F111: Djb | G111: Leha(Gofa) | H111: MGR | I111: 45667 | J111: 75.4077 | K111: =I111*J111 -> 3443643.4
A112: 13 | B112: 793663 | C112: 45493 | D112: Ayalneh Asefa | E112: 3-81046/24745 | F112: Djb | G112: Metu(Elibaboura | H112: AGO | I112: 50550 | J112: 76.5447 | K112: =I112*J112 -> 3869334.6
A113: 14 | B113: 796212 | C113: 45498 | D113: Tesfemariam Birhane | E113: 3-98387/29971 | F113: Djb | G113: Gesuba(Welaita | H113: AGO | I113: 46811 | J113: 76.5447 | K113: =I113*J113 -> 3583134
A114: 15 | B114: 796916 | C114: 45501 | D114: Getachew Alemshet | E114: 3-90951/27927 | F114: Djb | G114: Batu(Coustc | H114: HFO | I114: 45961 | J114: 57.7473 | K114: =I114*J114 -> 2654123.7
A115: 16 | B115: 797320 | C115: 45501 | D115: Destalem Abreha | E115: 3-71435/21297 | F115: Djb | G115: Dubti(Afar) | H115: AGO | I115: 46860 | J115: 76.5447 | K115: =I115*J115 -> 3586884.6
A116: 17 | B116: 797987 | C116: 45503 | D116: Musa Adem | E116: 3-94462/28942 | F116: Djb | G116: Baeker | H116: AGO | I116: 45963 | J116: 76.5447 | K116: =I116*J116 -> 3518224
A117: 18 | B117: 798914 | C117: 45504 | D117: Kasahun Tona | E117: 3-93024/28706 | F117: Djb | G117: Metu(Elibaboura | H117: MGR | I117: 45726 | J117: 75.4077 | K117: =I117*J117 -> 3448092.5
A118: 19 | B118: 797574 | C118: 45507 | D118: Sintayehu Esheta | E118: 3-91450/27736 | F118: Djb | G118: Gonder bikil F | H118: HFO | I118: 48094 | J118: 57.7473 | K118: =I118*J118 -> 2777298.6
A119: 20 | B119: 799506 | C119: 45510 | D119: Abebe Teka | E119: 3-94456/28742 | F119: Djb | G119: Gesuba(Welaita | H119: MGR | I119: 45780 | J119: 75.4077 | K119: =I119*J119 -> 3452164.5
A120: 21 | B120: 801261 | C120: 45512 | D120: Niguse Tadese | E120: 3-93449/28749 | F120: Djb | G120: Batu(Coustc | H120: HFO | I120: 45771 | J120: 57.7473 | K120: =I120*J120 -> 2643151.7
A121: 22 | B121: 802080 | C121: 45516 | D121: Teweldebrhan Gebrezgabi | E121: 3-93601/28714 | F121: Djb | G121: Mito(Silta) | H121: MGR | I121: 45688 | J121: 75.4077 | K121: =I121*J121 -> 3445227
... A125: 26 | B125: 805662 | C125: 45525 | D125: Teshome Tesfaye | E125: 3-93434/28741 | F125: Djb | G125: Metu(Elibaboura | H125: AGO | I125: 45948 | J125: 76.5447 | K125: =I125*J125 -> 3517075.9
A126: 27 | B126: 806442 | C126: 45526 | D126: Nigus Birhane | E126: 3-89959/27428 | F126: Djb | G126: Awash (Epse | H126: AGO | I126: 47253 | K126: =I126*J126 -> 0
A127: 28 | B127: 806904 | C127: 45527 | D127: Destalem Abreha | E127: 3-71435/21297 | F127: Djb | G127: Awash (Epse | H127: AGO | I127: 46854 | K127: =I127*J127 -> 0
A128: 29 | B128: 807109 | C128: 45528 | D128: Teweldebrhan Gebrezgabi | E128: 3-93601/28714 | F128: Djb | G128: Mito(Silta) | H128: AGO | I128: 45927 | J128: 76.5447 | K128: =I128*J128 -> 3515468.4
A129: 30 | B129: 805665 | C129: 45531 | D129: Getachew Alemshet | E129: 3-90951/27927 | F129: Djb | G129: Leha(Gofa) | H129: MGR | I129: 45833 | J129: 75.4077 | K129: =I129*J129 -> 3456161.1
A130: 31 | B130: 809553 | C130: 45535 | D130: Gebrezgabher Teweidebr | E130: 3-93024/28706 | F130: Djb | G130: Gesuba(Welaita) | H130: MGR | I130: 45892 | J130: 75.4077 | K130: =I130*J130 -> 3460610.2
A131: 32 | B131: 809183 | C131: 45535 | D131: Niguse Tadese | E131: 3-93449/28749 | F131: Djb | G131: Dashen(Gonder) | H131: LHF | I131: 46344 | J131: 58.9894 | K131: =I131*J131 -> 2733804.8
A132: 33 | B132: 772808 | C132: 45538 | D132: Endalk Kibret | E132: 3-93865/29153 | F132: Djb | G132: Awash (Epse | H132: AGO | I132: 48078 | K132: =I132*J132 -> 0
A133: 34 | B133: 810608 | C133: 45539 | D133: Abebe Teka | E133: 3-94456/28742 | F133: Djb | G133: Gesuba(Welaita | H133: AGO | I133: 46058 | J133: 76.5447 | K133: =I133*J133 -> 3525495.8
A134: 35 | B134: 811070 | C134: 45543 | D134: Andualem Demoz | E134: 3-90870/27584 | F134: Djb | G134: Metu(Elibaboura | H134: MGR | I134: 45431 | J134: 75.4077 | K134: =I134*J134 -> 3425847.2
A135: 36 | B135: 812527 | C135: 45544 | D135: Tesfemariam Birhane | E135: 3-98387/29971 | F135: Djb | G135: Awash (EPSE) | H135: AGO | I135: 46869 | K135: =I135*J135 -> 0
A136: 37 | B136: 812742 | C136: 45544 | D136: Nigus Birhane | E136: 3-89959/27428 | F136: Djb | G136: Awash (EPSE) | H136: AGO | I136: 47287 | K136: =I136*J136 -> 0
A137: 38 | B137: 812861 | C137: 45544 | D137: Destalem Abreha | E137: 3-71435/21297 | F137: Djb | G137: Awash (EPSE) | H137: AGO | I137: 46858 | K137: =I137*J137 -> 0
A138: 39 | B138: 813257 | C138: 45546 | D138: Weldekidan Hailu | E138: 3-98388/29973 | F138: Djb | G138: Leha(Gofa) | H138: AGO | I138: 46608 | J138: 76.5447 | K138: =I138*J138 -> 3567595.4
A139: 40 | B139: 811543 | C139: 45548 | D139: Teweldebrhan Gebrezgabi | E139: 3-93601/28714 | F139: Djb | G139: Mito(Silta) | H139: MGR | I139: 45598 | J139: 75.4077 | K139: =I139*J139 -> 3438440.3
A140: 41 | B140: 814019 | C140: 45549 | D140: Musa Adem | E140: 3-94462/28942 | F140: Djb | G140: Baeker | H140: AGO | I140: 46001 | J140: 76.5447 | K140: =I140*J140 -> 3521132.7
A141: 42 | B141: 816619 | C141: 45555 | D141: Teshome Tesfaye | E141: 3-93434/28741 | F141: Djb | G141: Batu(Coustc | H141: HFO | I141: 46036 | J141: 57.7473 | K141: =I141*J141 -> 2658454.7
A142: 43 | B142: 818517 | C142: 45560 | D142: Gebrezgabher Teweidebr | E142: 3-93024/28706 | F142: Djb | G142: Gesuba(Welaita | H142: MGR | I142: 45957 | J142: 75.4077 | K142: =I142*J142 -> 3465511.7
...

Sheet Gesuba(Welaita)
A2: Advance collected from fuel station :
A4: SN | B4: Date | C4: Bank | D4: Reference | E4: Description | K4: Amounts
D5: Transfer From Last Year | K5: 8507482
A6: 1 | B6: 45488 | C6: CBE | D6: Ft24197LY4T9 | E6: Advance Collction | K6: 2770000
A7: 2 | B7: 45497 | C7: CBE | D7: FT24206D0W4K | E7: Advance Collction | K7: 2000000
A8: 3 | B8: 45497 | C8: Awash | D8: 013041164408600 | E8: Advance Collction | K8: 2000000
A9: 4 | B9: 45506 | C9: Awash | D9: 013041164408600 | E9: Advance Collction | K9: 1400000
A10: 5 | B10: 45513 | C10: CBE | D10: FT24222V6WPO | E10: Advance Collction | K10: 1000000
A11: 6 | B11: 45513 | C11: Awash | D11: 013041164408600 | E11: Advance Collction | K11: 1000000
A12: 7 | B12: 45517 | C12: CBE | D12: FT242267WCQ | E12: Advance Collction | K12: 2000000
A13: 8 | B13: 45517 | C13: Abysinya | D13: FT24226K01X5 | E13: Advance Collction | K13: 850000
A14: 9 | B14: 45525 | C14: CBE | D14: FT24234YZ25V | E14: Advance Collction | K14: 700000
A15: 10 | B15: 45525 | C15: Abysinya | D15: FT24234LWN5K | E15: Advance Collction | K15: 600000
A16: 11 | B16: 45539 | C16: CBE | D16: FT242480X6PG | E16: Advance Collction | K16: 1900000
A17: 12 | B17: 45539 | C17: Abysinya | D17: FT24248MXLCS | E17: Advance Collction | K17: 500000
... A30: 25 | B30: 45616 | C30: Abysinya | D30: FT2432546GTW | E30: Advance Collction Customer | K30: 1000000
A31: 26 | B31: 45631 | C31: Berhan | D31: 1.7333824e+16 | E31: Advance Collction Customer | K31: 1500000
A32: 27 | B32: 45631 | C32: Abysinya | D32: FT243409Y872 | E32: Advance Collction Customer | K32: 400000
A33: 28 | B33: 45631 | C33: Abysinya | D33: FT24340D30YH | E33: Advance Collction Customer | K33: 200000
A34: 29 | B34: 45631 | C34: CBE | D34: FT243403GZ8D | E34: Advance Collction Customer | K34: 2300000
A35: 30 | B35: 45643 | C35: Dashen | D35: 649FTRQ2435200WU | E35: Advance Collction Customer | K35: 4000000
A36: 31
A37: 32
A38: 33
A39: 34
A40: 35
A41: 36
A42: 37
A43: 38
A44: 39
A45: 40
A46: 41 | K46: =SUM(K5:K44) -> 58777482
E51: Fuel Sales for fuel station
B53: FDC# | C53: Loading Date | E53: Truck/Semi Trailor Plate No | F53: Origin | G53: Destination | H53: Type of Product | I53: QTY at 20 F | J53: Rate Per Litrs | K53: Total fuel Cost Amount (In Birr) (G= E*F)
D54: Driver's Name
A55: 1 | B55: 790007 | C55: 45482 | D55: Sintayehu Habtamu | E55: 3-91450/27736 | F55: Djb | G55: Gesuba(Welayta) | H55: MGR | I55: 47580 | J55: 79.2292 | K55: =I55*J55 -> 3769725.3
A56: 2 | B56: 796212 | C56: 45501 | D56: Tesfemariam Birhane | E56: 3-98387/29971 | F56: Djibouti | G56: Gesuba(Welayta) | H56: AGO | I56: 46811 | J56: 84.3292 | K56: =I56*J56 -> 3947534.2
A57: 3 | B57: 799506 | C57: 45510 | D57: Abebe Teka | E57: 3-94456/28742 | F57: Djibouti | G57: Gesuba(Welayta) | H57: MGR | I57: 45780 | J57: 83.1892 | K57: =I57*J57 -> 3808401.6
A58: 4 | B58: 803539 | C58: 45519 | D58: Ayalneh Asefa | E58: 3-81046/24745 | F58: Djibouti | G58: Gesuba(Welayta) | H58: AGO | I58: 50662 | J58: 84.3292 | K58: =I58*J58 -> 4272285.9
A59: 5 | B59: 809553 | C59: 45534 | D59: Gebrezgabher Teweldebrhan | E59: 3-93024/28706 | F59: Djibouti | G59: Gesuba(Welayta) | H59: MGR | I59: 45892 | J59: 83.1892 | K59: =I59*J59 -> 3817718.8
A60: 6 | B60: 810608 | C60: 45539 | D60: Abebe Teka | E60: 3-94456/28742 | F60: Djibouti | G60: Gesuba(Welayta) | H60: AGO | I60: 46058 | J60: 84.3292 | K60: =I60*J60 -> 3884034.3
A61: 7 | B61: 818517 | C61: 45560 | D61: Gebrezgabher Teweldebrhan | E61: 3-93024/28706 | F61: Djibouti | G61: Gesuba(Welayta) | H61: MGR | I61: 45957 | J61: 83.1892 | K61: =I61*J61 -> 3823126.1
A62: 8 | B62: 819018 | C62: 45563 | D62: Teweidebrhan G/zgabher | E62: 3-93601/28714 | F62: Djibouti | G62: Gesuba(Welayta) | H62: AGO | I62: 45918 | J62: 84.3292 | K62: =I62*J62 -> 3872228.2
A63: 9 | B63: 822666 | C63: 45578 | D63: Andualem Demoz | E63: 3-90870/27584 | F63: Djibouti | G63: Gesuba(Welayta) | H63: MGR | I63: 45657 | J63: 91.7692 | K63: =I63*J63 -> 4189906.4
A64: 10 | B64: 823790 | C64: 45582 | D64: Destealem Abreha | E64: 3-71435/21297 | F64: Djibouti | G64: Gesuba(Welayta) | H64: AGO | I64: 46935 | J64: 90.9092 | K64: =I64*J64 -> 4266823.3
A65: 11 | B65: 833746 | C65: 45608 | D65: Gebrezgabher Teweldebrhan | E65: 3-93024/28706 | F65: Djibouti | G65: Gesuba(Welayta) | H65: MGR | I65: 46127 | J65: 91.7692 | K65: =I65*J65 -> 4233037.9
A66: 12 | B66: 842510 | C66: 45626 | D66: Birhane/Gebrezgabher | E66: 3-93573/28711 | F66: Djibouti | G66: Gesuba(Welayta) | H66: AGO | I66: 46152 | J66: 90.9092 | K66: =I66*J66 -> 4195641.4
A67: 13 | B67: 852830 | C67: 45657 | D67: Teweidebrhan G/zgabher | E67: 3-93601/28714 | F67: Djibouti | G67: Gesuba(Welayta) | H67: AGO | I67: 46155 | J67: 90.9092 | K67: =I67*J67 -> 4195914.1
A68: 14 | F68: Djibouti | G68: Gesuba(Welayta) | K68: =I68*J68 -> 0
A69: 15 | F69: Djibouti | G69: Gesuba(Welayta) | K69: =I69*J69 -> 0
A70: 16 | F70: Djibouti | G70: Gesuba(Welayta) | K70: =I70*J70 -> 0
A71: 17 | F71: Djibouti | G71: Gesuba(Welayta) | K71: =I71*J71 -> 0
K72: =SUM(K55:K71) -> 52276377
E75: Grand Total fuels sales | G75: Gesuba | K75: =K72 -> 52276377 | O75: =K31-K72 -> -50776377
E77: Account Receivable(Payable ) | G77: Gesuba | K77: =K46-K72 -> 6501104.6

Sheet Metu(Elibabora)
A2: Advance collected from fuel station :
A4: SN | B4: Date | C4: Bank | D4: Reference | E4: Description | K4: Amounts
E5: Transfer From the Last year | K5: 4045926.2
A6: 1 | B6: 45483 | C6: CBE | D6: FT24192SC690 | K6: 4000000
A7: 2 | B7: 45490 | C7: CBE | D7: FT24199540P3 | K7: 4000000
A8: 2 | B8: 45499 | C8: CBE | D8: FT24208M5Z1K | K8: 4000000
A9: 3 | B9: 45516 | C9: CBE | D9: FT24225930Z1 | K9: 4000000
A10: 4 | B10: 45523 | C10: CBE | D10: FT24232D5H31 | K10: 4000000
A11: 5 | B11: 45533 | C11: CBE | D11: FT24242DS235 | K11: 4000000
A12: 6 | B12: 45554 | C12: CBE | D12: FT24263N0FV2 | K12: 4000000
A13: 7 | B13: 45561 | C13: CBE | D13: FT24270JPHS4 | K13: 2000000
A14: 8 | B14: 45567 | C14: CBE | D14: FT242763YLBF | K14: 2100000
A15: 9 | B15: 45582 | C15: CBE | D15: FT2429163WXL | K15: 4300000
A16: 10 | B16: 45586 | C16: CBE | D16: FT24295FLJXY | K16: 4300000
A17: 11 | B17: 45604 | C17: CBE | D17: FT24313QP6DB | K17: 4300000
... A19: 13 | B19: 45640 | C19: CBE | D19: FT24349TGMGB | K19: 4300000
A20: 14 | K20: 3000000
A21: 15
A22: 16
A23: 17
A24: 18
A25: 19
A26: 20
A27: 21
A28: 22
A29: 23
A30: 24
A31: 25
A32: 26
... A50: 44
E51: Total Advance collected | K51: =SUM(K5:K49) -> 60645926
E55: Fuel Sales for fuel station | M55: 11545926
A58: SN | B58: FDC# | C58: Loading Date | E58: Truck/Semi Trailor Plate No | F58: Origin | G58: Destination | H58: Type of Product | I58: QTY at 20 F | J58: Rate Per Litrs | K58: Total fuel Cost Amount (In Birr) (G= E*F)
D59: Driver's Name
A60: 1 | B60: 793663 | C60: 45493 | D60: Ayalneh Asefa | E60: 3-81046/24745 | F60: Djibouti | G60: Metu(Elibaboura | H60: AGO | I60: 50550 | J60: 85.8792 | K60: =I60*J60 -> 4341193.6
A61: 2 | B61: 796914 | C61: 45504 | D61: Kasahun Tona | E61: 3-93024/28706 | F61: Djibouti | G61: Metu(Elibaboura | H61: MGR | I61: 45726 | J61: 84.7392 | K61: =I61*J61 -> 3874784.7
A62: 3 | B62: 803064 | C62: 45519 | D62: Tesfemariam Birhane | E62: 3-98387/29971 | F62: Djibouti | G62: Metu(Elibaboura | H62: AGO | I62: 46860 | J62: 85.8792 | K62: =I62*J62 -> 4024299.3
A63: 4 | B63: 805662 | C63: 45525 | D63: Teshome Tesfaye | E63: 3-93434/28741 | F63: Djibouti | G63: Metu(Elibaboura | H63: AGO | I63: 45948 | J63: 85.8792 | K63: =I63*J63 -> 3945977.5
A64: 5 | B64: 811070 | C64: 45543 | D64: Andualem Demoz | E64: 3-90870/27584 | F64: Djibouti | G64: Metu(Elibaboura | H64: MGR | I64: 45431 | J64: 84.7392 | K64: =I64*J64 -> 3849786.6
A65: 6 | B65: 818476 | C65: 45562 | D65: Abebe Teka | E65: 3-94456/28742 | F65: Djibouti | G65: Metu(Elibaboura | H65: AGO | I65: 46063 | J65: 85.8792 | K65: =I65*J65 -> 3955853.6
A66: 7 | B66: 821257 | C66: 45574 | D66: Gebrezgabher Teweldebrhan | E66: 3-93024/28706 | F66: Djibouti | G66: Metu(Elibaboura | H66: MGR | I66: 45867 | J66: 93.3592 | K66: =I66*J66 -> 4282106.4
A67: 8 | B67: 826247 | C67: 45584 | D67: Birhane G/ezgabher | E67: 3-93573/28711 | F67: Djibouti | G67: Metu(Elibaboura | H67: AGO | I67: 46155 | J67: 92.4992 | K67: =I67*J67 -> 4269300.6
A68: 9 | B68: 827682 | C68: 45592 | D68: Teshome Tesfaye | E68: 3-93434/28741 | F68: Djibouti | G68: Metu(Elibaboura | H68: MGR | I68: 45862 | J68: 93.3592 | K68: =I68*J68 -> 4281639.6
A69: 10 | B69: 837311 | C69: 45615 | D69: Teweldebrhan Gebrezgabi | E69: 3-93601/28714 | F69: Djibouti | G69: Metu(Elibaboura | H69: AGO | I69: 46127 | J69: 92.4992 | K69: =I69*J69 -> 4266710.6
A70: 11 | B70: 841385 | C70: 45631 | D70: Gebrezgabher Teweidebr | E70: 3-93024/28706 | F70: Djibouti | G70: Metu(Elibaboura | H70: MGR | I70: 46204 | J70: 93.3592 | K70: =I70*J70 -> 4313568.5
A71: 12 | B71: 848146 | C71: 45642 | D71: Teweldebrhan Gebrezgabi | E71: 3-93601/28714 | F71: Djibouti | G71: Metu(Elibaboura | H71: AGO | I71: 46300 | J71: 92.4992 | K71: =I71*J71 -> 4282713
A72: 13 | B72: 852828 | C72: 45654 | D72: Nigus Birhane | E72: 3-89959/27428 | F72: Djibouti | G72: Metu(Elibaboura | H72: AGO | I72: 47642 | J72: 92.4992 | K72: =I72*J72 -> 4406846.9
A73: 14 | F73: Djibouti | K73: =I73*J73 -> 0
A74: 23 | F74: Djibouti | K74: =I74*J74 -> 0
A75: 24 | F75: Djibouti | K75: =I75*J75 -> 0
A76: 25 | F76: Djibouti | K76: =I76*J76 -> 0
A77: 26 | F77: Djibouti | K77: =I77*J77 -> 0
A78: total | K78: =SUM(K60:K77) -> 54094781
E84: Grand Total fuels sales | K84: =K78 -> 54094781
E86: Account Receivable(Payable ) | K86: =K51-K78 -> 6551145.4

Sheet Leha(Gofa)
A2: Advance collected from fuel station :
A4: SN | B4: Date | C4: Bank | D4: Reference | E4: Description | K4: Amounts
E5: Transfer From Last Year | K5: 9113228.5
A6: 1 | B6: 45499 | C6: Birhan | D6: 2500570132961 | E6: Advance Collection | K6: 4000000
A7: 2 | B7: 45513 | C7: Birhan | D7: 3012408095157684 | E7: Advance Collection Outgoing RTGS Advice to 1000547269989 | K7: 2500000
A8: 3 | B8: 45524 | C8: Birhan | D8: 3012408202582143 | E8: Advance Collection Outgoing RTGS Advice to 1000547269989 | K8: 3000000
A9: 4 | B9: 45537 | C9: Birhan | D9: 3012409026196526 | E9: Advance Collection Outgoing RTGS Advice to 1000628923527 | K9: 4000000
A10: 5 | B10: 45546 | C10: Birhan | D10: 2500570132961 | E10: Advance Collection | K10: 4000000
A11: 6 | B11: 45572 | C11: Birhan | D11: 2500570132961 | E11: Advance Collection | K11: 2000000
A12: 7 | B12: 45579 | C12: Birhan | D12: 2500570132961 | E12: Advance Collection | K12: 4300000
A13: 8 | B13: 45609 | C13: Birhan | D13: 1731483783117173489 | E13: Advance Collection | K13: 4300000
A14: 9 | B14: 45625 | C14: CBE | D14: FT24334CP26X | E14: Advance Collection | K14: 4300000
A15: 10 | B15: 45652 | C15: CBE | D15: FT24361P3X32 | E15: Advance Collection | K15: 4300000
A16: 11
A17: 12
A18: 13
A19: 14
A20: 15
A21: 16
A22: 17
A23: 18
A24: 19
A25: 20
A26: 20
A27: 21
... A47: 41
P48: 13113228
E51: Total Advance collected | K51: =SUM(K5:K49) -> 45813228 | M51: 13113228
E55: Fuel Sales for fuel station
A58: SN | B58: FDC# | C58: Loading Date | E58: Truck/Semi Trailor Plate No | F58: Origin | G58: Destination | H58: Type of Product | I58: QTY at 20 F | J58: Rate Per Litrs | K58: Total fuel Cost Amount (In Birr) (G= E*F)
D59: Driver's Name
A60: 1 | B60: 790978 | C60: 45493 | D60: Niguse Tadese | E60: 3-93449/28749 | F60: Djibouti | G60: Leha(gofa) | H60: MGR | I60: 45667 | J60: 84.8792 | K60: =I60*J60 -> 3876178.4
A61: 2 | B61: 802099 | C61: 45517 | D61: Weldekidan.Hailu | E61: 3-98388/29973 | F61: Djibouti | G61: Leha(gofa) | H61: AGO | I61: 46632 | J61: 86.0192 | K61: =I61*J61 -> 4011247.3
A62: 3 | B62: 805665 | C62: 45531 | D62: Getachew Alemshet | E62: 3-90951/27927 | F62: Djibouti | G62: Leha(gofa) | H62: MGR | I62: 45833 | J62: 84.8792 | K62: =I62*J62 -> 3890268.4
A63: 4 | B63: 813257 | C63: 45546 | D63: Weldekidan.Hailu | E63: 3-98388/29973 | F63: Djibouti | G63: Leha(gofa) | H63: AGO | I63: 46608 | J63: 86.0192 | K63: =I63*J63 -> 4009182.9
A64: 5 | B64: 821689 | C64: 45576 | D64: Tesfemariam Birhane | E64: 3-98387/29971 | F64: Djibouti | G64: Leha(gofa) | H64: MGR | I64: 46628 | J64: 93.4992 | K64: =I64*J64 -> 4359680.7
A65: 6 | B65: 823475 | C65: 45576 | D65: Nigus Tadese | E65: 3-93449/28749 | F65: Djibouti | G65: Leha(gofa) | H65: AGO | I65: 46048 | J65: 92.6392 | K65: =I65*J65 -> 4265849.9
A66: 7 | B66: 834606 | C66: 45605 | D66: Weldekidan.Hailu | E66: 3-98388/29973 | F66: Djibouti | G66: Leha(gofa) | H66: AGO | I66: 46552 | J66: 92.6392 | K66: =I66*J66 -> 4312540
A67: 8 | B67: 844579 | C67: 45633 | D67: Weldekidan.Hailu | E67: 3-98388/29973 | F67: Djibouti | G67: Leha(gofa) | H67: AGO | I67: 46755 | J67: 92.6392 | K67: =I67*J67 -> 4331345.8
A68: 9 | F68: Djibouti | K68: =I68*J68 -> 0
A69: 10 | F69: Djibouti | K69: =I69*J69 -> 0
A70: 11 | F70: Djibouti | K70: =I70*J70 -> 0
A71: 12 | F71: Djibouti | K71: =I71*J71 -> 0
A72: 13 | F72: Djibouti | K72: =I72*J72 -> 0
A73: 14 | F73: Djibouti | K73: =I73*J73 -> 0
A74: 15 | F74: Djibouti | K74: =I74*J74 -> 0
A75: 16 | F75: Djibouti | K75: =I75*J75 -> 0
A76: 17 | F76: Djibouti | K76: =I76*J76 -> 0
A77: 18 | F77: Djibouti | K77: =I77*J77 -> 0
A78: 19 | F78: Djibouti | K78: =I78*J78 -> 0
A79: 20 | F79: Djibouti | K79: =I79*J79 -> 0
... A85: 26 | F85: Djibouti | K85: =I85*J85 -> 0
A86: total | K86: =SUM(K60:K85) -> 33056293
E92: Grand Total fuels sales | K92: =K86 -> 33056293
E94: Account Receivable(Payable ) | K94: =K51-K86 -> 12756935

Sheet Mito(Silta)
A2: Advance collected from fuel station :
A4: SN | B4: Date | C4: Bank | D4: Reference | E4: Description | K4: Amounts
E5: Transfer From the last year | K5: 4035574.2
A6: 1 | B6: 45505 | C6: Dashen | D6: FT8FTRQ242140008 | K6: 4000000
A7: 2 | B7: 45519 | C7: Dashen | D7: F78FTRQ2422800WK | K7: 2000000
A8: 2 | B8: 45523 | C8: Dashen | D8: FT8FTRQ2423200WC | K8: 2000000
A9: 3 | B9: 45537 | C9: Dashen | D9: FT8FTRQ2424600Wq | K9: 3386280.4
A10: 4 | B10: 45559 | C10: Dashen | D10: F78FTRQ24800Wn | K10: 3800000
A11: 5 | B11: 45574 | C11: Dashen | D11: FT8FTRQ242830007 | K11: 3900000
A12: 6 | B12: 45576 | C12: Dashen | D12: FT8FTRQ2428500WH | K12: 200000
A13: 7 | B13: 45601 | C13: Dashen | D13: FT8FTRQ24310000U | K13: 4100000
A14: 8 | B14: 45601 | C14: Dashen | D14: FT8FTRQ24310000D | K14: 200000
A15: 9 | B15: 45612 | C15: Dashen | D15: F78FTRQ24321000E | K15: 4300000
A16: 10 | B16: 45636 | C16: Dashen | D16: FT8FTRQ2434500WW | K16: 1500000
A17: 11 | B17: 45642 | C17: Dashen | D17: FT8FTRQ243510015 | K17: 2500000
A18: 12
A19: 13
A20: 14
A21: 15
A22: 16
A23: 17
A24: 18
A25: 19
A26: 20
A27: 21
A28: 22
A29: 23
... A47: 41
E51: Total Advance collected | K51: =SUM(K5:K50) -> 35921855
E55: Fuel Sales for fuel station
A58: SN | B58: FDC# | C58: Loading Date | E58: Truck/Semi Trailor Plate No | F58: Origin | G58: Destination | H58: Type of Product | I58: QTY at 20 F | J58: Rate Per Litrs | K58: Total fuel Cost Amount (In Birr) (G= E*F)
D59: Driver's Name
A60: 1 | B60: 789278 | C60: 45481 | D60: Destalem Abreha | E60: 3-71435/21297 | F60: Djib0uti | G60: Mito(Silta) | H60: MGR | I60: 46483 | J60: 82.3292 | K60: =I60*J60 -> 3826908.2
A61: 2 | B61: 802080 | C61: 45516 | D61: Teweldebrhan G/zgabher | E61: 3-93601/28714 | F61: Djib0uti | G61: Mito(Silta) | H61: MGR | I61: 45688 | J61: 82.3292 | K61: =I61*J61 -> 3761456.5
A62: 3 | B62: 807109 | C62: 45528 | D62: Teweldebrhan G/zgabher | E62: 3-93601/28714 | F62: Djib0uti | G62: Mito(Silta) | H62: AGO | I62: 45927 | J62: 83.4692 | K62: =I62*J62 -> 3833489.9
A63: 4 | B63: 811543 | C63: 45548 | D63: Teweldebrhan G/zgabher | E63: 3-93601/28714 | F63: Djib0uti | G63: Mito(Silta) | H63: MGR | I63: 45598 | J63: 82.3292 | K63: =I63*J63 -> 3754046.9
A64: 5 | B64: 821685 | C64: 45571 | D64: Teshome Tesfaye | E64: 3-93434/28741 | F64: Djib0uti | G64: Mito(Silta) | H64: AGO | I64: 45905 | J64: 83.4692 | K64: =I64*J64 -> 3831653.6
A65: 6 | B65: 829745 | C65: 45591 | D65: Teweldebrhan G/zgabher | E65: 3-93601/28714 | F65: Djib0uti | G65: Mito(Silta) | H65: AGO | I65: 46082 | J65: 90.0192 | K65: =I65*J65 -> 4148264.8
A66: 7 | B66: 838248 | C66: 45616 | D66: Teshome Tesfaye | E66: 3-93434/28741 | F66: Djib0uti | G66: Mito(Silta) | H66: AGO | I66: 46204 | J66: 90.0192 | K66: =I66*J66 -> 4159247.1
A67: 8 | B67: 848143 | C67: 45656 | D67: Teshome Tesfaye | E67: 3-93434/28741 | F67: Djib0uti | G67: Mito(Silta) | H67: MGR | I67: 46077 | J67: 90.8792 | K67: =I67*J67 -> 4187440.9
A68: 9 | F68: Djib0uti | K68: =I68*J68 -> 0
A69: 10 | F69: Djib0uti | K69: =I69*J69 -> 0
A70: 11 | F70: Djib0uti | K70: =I70*J70 -> 0
A71: 12 | F71: Djib0uti | K71: =I71*J71 -> 0
A72: 13 | F72: Djib0uti | K72: =I72*J72 -> 0
A73: 14 | F73: Djib0uti | K73: =I73*J73 -> 0
A74: 15 | F74: Djib0uti | K74: =I74*J74 -> 0
A75: 16 | F75: Djib0uti | K75: =I75*J75 -> 0
A76: 17 | F76: Djib0uti | K76: =I76*J76 -> 0
A77: 18 | F77: Djib0uti | K77: =I77*J77 -> 0
A78: 19 | F78: Djib0uti | K78: =I78*J78 -> 0
A79: 20 | F79: Djib0uti | K79: =I79*J79 -> 0
... A84: 25 | F84: Djib0uti | K84: =I84*J84 -> 0
A85: 26 | F85: Djib0uti
A86: total | K86: =SUM(K60:K85) -> 31502508
E89: Grand Total fuels sales | K89: =K86 -> 31502508
E91: Account Receivable(Payable ) | K91: =K51-K89 -> 4419346.7

Sheet Batu(Coustic Soda)
A2: Advance collected from fuel station :
A4: SN | B4: Date | C4: Bank | D4: Reference | E4: Description | K4: Amounts
E5: Transfer From Last year | K5: 2991274.8
A6: 1 | B6: 45498 | C6: CBE | D6: FT24207W59Q3 | E6: Advance Collection | K6: 6165120
A7: 2 | B7: 45509 | C7: CBE | D7: FT242185JRT9 | E7: Advance Collection | K7: 3082560
A8: 2
A9: 3
A10: 4
A11: 5
A12: 6
A13: 7
A14: 8
A15: 9
A16: 10
A17: 11
A18: 12
A19: 13
... A47: 41
E51: Total Advance collected | K51: =SUM(K5:K47) -> 12238955
E55: Fuel Sales for fuel station
A58: SN | B58: FDC# | C58: Loading Date | E58: Truck/Semi Trailor Plate No | F58: Origin | G58: Destination | H58: Type of Product | I58: QTY at 20 F | J58: Rate Per Litrs | K58: Total fuel Cost Amount (In Birr) (G= E*F)
D59: Driver's Name
A60: 1 | B60: 786564 | C60: 45487 | D60: Wedneh Bekele | E60: 3-93601/28714 | F60: Djibouti | G60: Batu(Coustic | H60: HFO | I60: 45946 | J60: 64.31 | K60: =I60*J60 -> 2954787.3
A61: 2 | B61: 796916 | C61: 45501 | D61: Getachew Alemshet | E61: 3-90951/27927 | F61: Djibouti | G61: Batu(Coustic | H61: HFO | I61: 45961 | J61: 64.31 | K61: =I61*J61 -> 2955751.9
A62: 3 | B62: 801261 | C62: 45512 | D62: Nigus Tadese | E62: 3-93449/28749 | F62: Djibouti | G62: Batu(Coustic | H62: HFO | I62: 45771 | J62: 64.31 | K62: =I62*J62 -> 2943533
A63: 4 | B63: 816619 | C63: 45555 | D63: Teshome Tesfaye | E63: 3-93434/29741 | F63: Djibouti | G63: Batu(Coustic | H63: HFO | I63: 46036 | J63: 64.31 | K63: =I63*J63 -> 2960575.2
A64: 5 | F64: Djibouti | K64: =I64*J64 -> 0
A65: 6 | F65: Djibouti | K65: =I65*J65 -> 0
A66: 7 | F66: Djibouti | K66: =I66*J66 -> 0
A67: 8 | F67: Djibouti | K67: =I67*J67 -> 0
A68: 9 | F68: Djibouti | K68: =I68*J68 -> 0
A69: 10 | F69: Djibouti | K69: =I69*J69 -> 0
A70: 11 | F70: Djibouti | K70: =I70*J70 -> 0
A71: 12 | F71: Djibouti | K71: =I71*J71 -> 0
A72: 13 | F72: Djibouti | K72: =I72*J72 -> 0
A73: 14 | F73: Djibouti | K73: =I73*J73 -> 0
A74: 15 | F74: Djibouti | K74: =I74*J74 -> 0
A75: 16 | F75: Djibouti | K75: =I75*J75 -> 0
... A85: 26 | F85: Djibouti | K85: =I85*J85 -> 0
A86: total | K86: =SUM(K60:K85) -> 11814647
E92: Grand Total fuels sales | K92: =K86 -> 11814647
E94: Account Receivable(Payable ) | K94: =K51-K92 -> 424307.49

Sheet Dashine(Gonder)
F1: Dashine(Berwery) | H1: Factory
A2: Advance collected from fuel station :
A4: SN | B4: Date | C4: Bank | D4: Reference | E4: Description | K4: Amounts | L4: Loss | M4: Price | N4: Total Loss in birr | O4: Plate No
E5: Transfer From Last year | K5: 6795274.1 | L5: 3866 | M5: 64.95 | N5: =L5*M5 -> 251096.7 | O5: 3-93643
A6: 1 | B6: 45600 | C6: Abyssinya | D6: FT24278764RP | E6: Advance Collection Diller | K6: 10000000 | L6: 4087 | M6: 64.95 | N6: =L6*M6 -> 265450.65 | O6: 3-93045
A7: 2 | B7: 45600 | C7: Abyssinya | D7: FT2430928P4 | E7: Advance Collection Diller | K7: 5000000 | L7: 2920 | M7: 64.95 | N7: =L7*M7 -> 189654 | O7: 3-93449
A8: 2 | C8: Abyssinya | D8: FT2430928P4 | E8: Advance Collection Diller | K8: 5000000 | L8: 736 | M8: 64.95 | N8: =L8*M8 -> 47803.2 | O8: 3-90951
A9: 3 | B9: 45639 | C9: Abyssinya | D9: FT24348ZX59M | E9: Advance Collection Diller | K9: 8000000 | L9: 735 | M9: 64.95 | N9: =L9*M9 -> 47738.25 | O9: 3-93434
A10: 4 | N10: =SUM(N5:N9) -> 801742.8
A11: 5
A12: 6 | N12: =N10+K94 -> 8721007.4
A13: 7
A14: 8
A15: 9
A16: 10
A17: 11
A18: 12
A19: 13 | N19: =K5+N10 -> 7597016.9
A20: 14
A21: 15
A22: 16
A23: 17
A24: 18
A25: 19
A26: 20
A27: 21
A28: 22
A29: 23
A30: 24
A31: 25
... A47: 41
E51: Total Advance collected | K51: =SUM(K5:K50) -> 34795274
E55: Fuel Sales for fuel station
A58: SN | B58: FDC# | C58: Loading Date | E58: Truck/Semi Trailor Plate No | F58: Origin | G58: Destination | H58: Type of Product | I58: QTY at 20 F | J58: Rate Per Litrs | K58: Total fuel Cost Amount (In Birr) (G= E*F) | M58: New Price
D59: Driver's Name
A60: 1 | B60: 809183 | C60: 45535 | D60: Niguse Tadese | E60: 3-93449/28749 | F60: Djibouti | G60: Dashen(Gonder) | H60: LFO | I60: 46344 | J60: 64.95 | K60: =I60*J60 -> 3010042.8 | M60: 72.1
A61: 2 | B61: 821691 | C61: 45572 | D61: Endalk Kibret | E61: 3-93865/29153 | F61: Djibouti | G61: Dashen(Gonder) | H61: LFO | I61: 48448 | J61: 68.07 | K61: =I61*J61 -> 3297855.4 | M61: 106.84 | N61: Through A.A
A62: 3 | B62: 829003 | C62: 45590 | D62: Musa Adem | E62: 3-94462/28942 | F62: Djibouti | G62: Dashen(Gonder) | H62: LFO | I62: 46470 | J62: 102.97 | K62: =I62*J62 -> 4785015.9 | M62: 102.97 | N62: Through Weldya
A63: 4 | B63: 833747 | C63: 45604 | D63: Musa Adem | E63: 3-94462/28942 | F63: Djibouti | G63: Dashen(Gonder) | H63: LFO | I63: 46431 | J63: 102.97 | K63: =I63*J63 -> 4781000.1
A64: 5 | B64: 839955 | C64: 45620 | D64: Endalk Kibret | E64: 3-93865/29153 | F64: Djibouti | G64: Dashen(Gonder) | H64: LFO | I64: 48516 | J64: 111.84 | K64: =I64*J64 -> 5426029.4
A65: 6 | B65: 847619 | C65: 45641 | D65: Endalk Kibret | E65: 3-93865/29153 | F65: Djibouti | G65: Dashen(Gonder) | H65: LFO | I65: 47468 | J65: 117.47 | K65: =I65*J65 -> 5576066
A66: 7 | F66: Djibouti | K66: =I66*J66 -> 0
A67: 8 | F67: Djibouti | K67: =I67*J67 -> 0
A68: 9 | F68: Djibouti | K68: =I68*J68 -> 0
A69: 10 | F69: Djibouti | K69: =I69*J69 -> 0
A70: 11 | F70: Djibouti | K70: =I70*J70 -> 0
A71: 12 | F71: Djibouti | K71: =I71*J71 -> 0
A72: 13 | F72: Djibouti | K72: =I72*J72 -> 0
A73: 14 | F73: Djibouti | K73: =I73*J73 -> 0
A74: 15 | F74: Djibouti | K74: =I74*J74 -> 0
A75: 16 | F75: Djibouti | K75: =I75*J75 -> 0
A76: 17 | F76: Djibouti | K76: =I76*J76 -> 0
A77: 18 | F77: Djibouti | K77: =I77*J77 -> 0
... A85: 26 | F85: Djibouti | K85: =I85*J85 -> 0
A86: total | K86: =SUM(K60:K85) -> 26876010
E92: Grand Total fuels sales | K92: =K86 -> 26876010
E94: Account Receivable(Payable ) | K94: =K51-K92 -> 7919264.6
K96: 7073918.6
K98: =+K96-K94 -> -845346

Sheet Dubti(Sordo)
A2: Advance collected from fuel station :
A4: SN | B4: Date | C4: Bank | D4: Reference | E4: Description | K4: Amounts
A5: 1 | B5: 45507 | C5: CBE | D5: FT24216W1N!D | E5: Advance Collection | K5: 850000
A6: 2 | B6: 45511 | C6: CBE | D6: FT24220PrBKG | E6: Advance Collection | K6: 550000
A7: 2
A8: 3
A9: 4
A10: 5
A11: 6
A12: 7
A13: 8
A14: 9
A15: 10
A16: 11
A17: 12
A18: 13
... A46: 41
E47: Total Advance collected | K47: =SUM(K5:K46) -> 1400000
E54: Fuel Sales for fuel station
A57: SN | B57: FDC# | C57: Loading Date | E57: Truck/Semi Trailor Plate No | F57: Origin | G57: Destination | H57: Type of Product | I57: QTY at 20 F | J57: Rate Per Litrs | K57: Total fuel Cost Amount (In Birr) (G= E*F)
D58: Driver's Name
A59: 1 | B59: 797320 | C59: 45501 | D59: Destalem Abreha | E59: 3-71435/21297 | F59: Djibouti | G59: DubtiAfar | H59: AGO | I59: 46860 | J59: 79.4492 | K59: =I59*J59 -> 3722989.5
A60: 2 | F60: Djibouti
A61: 3 | F61: Djibouti
A62: 4 | F62: Djibouti
A63: 5 | F63: Djibouti
A64: 6 | F64: Djibouti
A65: 7 | F65: Djibouti
A66: 8 | F66: Djibouti
A67: 9 | F67: Djibouti
A68: 10 | F68: Djibouti
A69: 11 | F69: Djibouti
A70: 12 | F70: Djibouti
A71: 13 | F71: Djibouti
... A84: 26 | F84: Djibouti
A85: total | K85: =SUM(K59:K84) -> 3722989.5
E91: Grand Total fuels sales | K91: =K85 -> 3722989.5
E93: Account Receivable(Payable ) | K93: =K47-K91 -> -2322989.5

Sheet Mykadra
A2: Advance collected from fuel station :
A4: SN | B4: Date | C4: Bank | D4: Reference | E4: Description | K4: Amounts
A5: 1 | B5: 45495 | C5: CBE | D5: FT24204JHQ3N | E5: Advance Collection | K5: 1894000
A6: 2 | B6: 45495 | C6: Abysinya | D6: FT24204YJ4FC | E6: Advance Collection | K6: 854000
A7: 2 | B7: 45495 | C7: Abysinya | D7: FT242048N5T1 | E7: Advance Collection | K7: 374000
A8: 3 | B8: 45495 | C8: CBE | D8: FT242045RG4G | E8: Advance Collection | K8: 152000
A9: 4 | B9: 45496 | C9: CBE | E9: Advance Collection | K9: 321000
A10: 5
A11: 6
A12: 7
A13: 8
A14: 9
A15: 10
A16: 11
A17: 12
A18: 13
A19: 14
A20: 15
A21: 16
... A46: 41
E47: Total Advance collected | K47: =SUM(K5:K46) -> 3595000
E54: Fuel Sales for fuel station
A57: SN | B57: FDC# | C57: Loading Date | E57: Truck/Semi Trailor Plate No | F57: Origin | G57: Destination | H57: Type of Product | I57: QTY at 20 F | J57: Rate Per Litrs | K57: Total fuel Cost Amount (In Birr) (G= E*F)
D58: Driver's Name
A59: 1 | B59: 790976 | C59: 45485 | D59: Musa Adem | E59: 3-94462/28942 | F59: Djibouti | G59: Mykadra | H59: AGO | I59: 45977 | J59: 84.7892 | K59: =I59*J59 -> 3898353
A60: 2 | F60: Djibouti
A61: 3 | F61: Djibouti
A62: 4 | F62: Djibouti
A63: 5 | F63: Djibouti
A64: 6 | F64: Djibouti
A65: 7 | F65: Djibouti
A66: 8 | F66: Djibouti
A67: 9 | F67: Djibouti
A68: 10 | F68: Djibouti
A69: 11 | F69: Djibouti
A70: 12 | F70: Djibouti
A71: 13 | F71: Djibouti
... A84: 26 | F84: Djibouti
A85: total | K85: =SUM(K59:K84) -> 3898353
E91: Grand Total fuels sales | K91: =K85 -> 3898353
E93: Account Receivable(Payable ) | K93: =K47-K91 -> -303353.05

Sheet S.Humera
A2: Advance collected from fuel station :
A4: SN | B4: Date | C4: Bank | D4: Reference | E4: Description | K4: Amounts
A5: 1 | B5: 45630 | C5: Abysinya | D5: FT2433KIL5GUAY | E5: Advance Collected From Diler | K5: 1900000
A6: 2 | B6: 45630 | C6: Awash | D6: 013041164408600 | E6: Advance Collected From Diler | K6: 2100000
A7: 2 | B7: 45637 | C7: CBE | D7: FT24346L2FMW | E7: Advance Collected From Diler | K7: 3000000
A8: 3 | E8: Advance Collected From Diler
A9: 4 | E9: Advance Collected From Diler
A10: 5 | E10: Advance Collected From Diler
A11: 6 | E11: Advance Collected From Diler
A12: 7 | E12: Advance Collected From Diler
A13: 8 | E13: Advance Collected From Diler
A14: 9 | E14: Advance Collected From Diler
A15: 10 | E15: Advance Collected From Diler
A16: 11 | E16: Advance Collected From Diler
A17: 12 | E17: Advance Collected From Diler
A18: 13 | E18: Advance Collected From Diler
A19: 14 | E19: Advance Collected From Diler
... A22: 17 | E22: Advance Collected From Diler
A23: 18
A24: 19
A25: 20
A26: 21
A27: 22
A28: 23
A29: 24
A30: 25
A31: 26
A32: 27
A33: 28
A34: 29
... A46: 41
E47: Total Advance collected | K47: =SUM(K5:K46) -> 7000000
E54: Fuel Sales for fuel station
A57: SN | B57: FDC# | C57: Loading Date | E57: Truck/Semi Trailor Plate No | F57: Origin | G57: Destination | H57: Type of Product | I57: QTY at 20 F | J57: Rate Per Litrs | K57: Total fuel Cost Amount (In Birr) (G= E*F)
D58: Driver's Name
A59: 1 | B59: 839959 | C59: 45620 | D59: Getachew Alemshet | E59: 3-94462/27927 | F59: Djibouti | G59: S.Humera | H59: AGO | I59: 46264 | J59: 91.1992 | K59: =I59*J59 -> 4219239.8
A60: 2 | B60: 844221 | C60: 45636 | D60: Nigus Birhane | E60: 3-89959/27428 | F60: Djibouti | G60: S.Humera | H60: MGR | I60: 47305 | J60: 92.0592 | K60: =I60*J60 -> 4354860.5
A61: 3 | F61: Djibouti | K61: =I61*J61 -> 0
A62: 4 | F62: Djibouti | K62: =I62*J62 -> 0
A63: 5 | F63: Djibouti | K63: =I63*J63 -> 0
A64: 6 | F64: Djibouti | K64: =I64*J64 -> 0
A65: 7 | F65: Djibouti | K65: =I65*J65 -> 0
A66: 8 | F66: Djibouti | K66: =I66*J66 -> 0
A67: 9 | F67: Djibouti | K67: =I67*J67 -> 0
A68: 10 | F68: Djibouti | K68: =I68*J68 -> 0
A69: 11 | F69: Djibouti | K69: =I69*J69 -> 0
A70: 12 | F70: Djibouti | K70: =I70*J70 -> 0
A71: 13 | F71: Djibouti | K71: =I71*J71 -> 0
A72: 14 | F72: Djibouti | K72: =I72*J72 -> 0
... A79: 21 | F79: Djibouti | K79: =I79*J79 -> 0
A80: 22 | F80: Djibouti
A81: 23 | F81: Djibouti
A82: 24 | F82: Djibouti
A83: 25 | F83: Djibouti
A84: 26 | F84: Djibouti
A85: total | K85: =SUM(K59:K84) -> 8574100.2
E91: Grand Total fuels sales | K91: =K85 -> 8574100.2
E93: Account Receivable(Payable ) | K93: =K47-K91 -> -1574100.2

Sheet Adebay
A2: Advance collected from fuel station :
A4: SN | B4: Date | C4: Bank | D4: Reference | E4: Description | K4: Amounts
A5: 1 | B5: 45604 | C5: CBE | D5: FT243130XSSM | E5: Advance Collection | K5: 3300000
A6: 2 | B6: 45604 | C6: Awash | D6: 013041164408600 | E6: Advance Collection | K6: 1000000
A7: 2 | B7: 45614 | C7: CBE | D7: FT24323TH1GF | E7: Advance Collection From Dilers | K7: 2000000
A8: 3 | B8: 45614 | C8: Awash | D8: 013041164408600 | E8: Advance Collection From Dilers | K8: 2100000
A9: 4
A10: 5
A11: 6
A12: 7
A13: 8
A14: 9
A15: 10
A16: 11
A17: 12
A18: 13
A19: 14
A20: 15
... A46: 41
D50: Total Advance collected | K50: =SUM(K5:K45) -> 8400000
E54: Fuel Sales for fuel station
A56: SN | B56: FDC# | C56: Loading Date | E56: Truck/Semi Trailor Plate No | F56: Origin | G56: Destination | H56: Type of Product | I56: QTY at 20 F | J56: Rate Per Litrs | K56: Total fuel Cost Amount (In Birr) (G= E*F)
D57: Driver's Name
A58: 1 | B58: 834611 | C58: 45607 | D58: Sintayehu Esheta | E58: 3-91450/27736 | F58: Djibouti | G58: Adebay | H58: AGO | I58: 48475 | J58: 91.2992 | K58: =I58*J58 -> 4425728.7
A59: 2 | B59: 838249 | C59: 45618 | D59: Nigus Birhane | E59: 3-89959/27428 | F59: Djibouti | G59: Adebay | H59: MGR | I59: 47340 | J59: 92.1592 | K59: =I59*J59 -> 4362816.5
A60: 3 | F60: Djibouti | K60: =I60*J60 -> 0
A61: 4 | F61: Djibouti | K61: =I61*J61 -> 0
A62: 5 | F62: Djibouti | K62: =I62*J62 -> 0
A63: 6 | F63: Djibouti | K63: =I63*J63 -> 0
A64: 7 | F64: Djibouti | K64: =I64*J64 -> 0
A65: 8 | F65: Djibouti | K65: =I65*J65 -> 0
A66: 9 | F66: Djibouti | K66: =I66*J66 -> 0
A67: 10 | F67: Djibouti | K67: =I67*J67 -> 0
A68: 11 | F68: Djibouti | K68: =I68*J68 -> 0
A69: 12 | F69: Djibouti | K69: =I69*J69 -> 0
A70: 13 | F70: Djibouti | K70: =I70*J70 -> 0
A71: 14 | F71: Djibouti | K71: =I71*J71 -> 0
... A83: 26 | F83: Djibouti | K83: =I83*J83 -> 0
B84: total | K84: =SUM(K58:K83) -> 8788545.2
E90: Grand Total fuels sales | K90: =K84 -> 8788545.2
E92: Account Receivable(Payable ) | K92: =K50-K90 -> -388545.25

Sheet Baeker
A2: Advance collected from fuel station :
A4: SN | B4: Date | C4: Bank | D4: Reference | E4: Description | K4: Amounts
A5: 1 | B5: 45533 | C5: CBE | D5: FT2424265FC3 | E5: Collected From Others(Baro Tesfaye Yideg) | K5: 2000000
A6: 2 | B6: 45538 | C6: CBE | D6: FT24247FFZ3L | E6: Collected From Others(Baro Tesfaye Yideg) | K6: 1200000
A7: 2 | B7: 45548 | C7: CBE | D7: FT24257GZGWH | E7: Advance Collection | K7: 4000000
A8: 3 | B8: 45567 | C8: CBE | E8: Advance Collection | K8: 4000000
A9: 4 | B9: 45625 | C9: CBE | D9: FT24334GX1WW | E9: Advance Collection | K9: 3500000
A10: 5 | B10: 45625 | C10: Awash | D10: 013041164408600 | E10: Advance Collection | K10: 600000
A11: 6 | B11: 45651 | C11: Abysinya | D11: FT24360/24824 | E11: Advance Collection | K11: 12000000
A12: 7
A13: 8
A14: 9
A15: 10
A16: 11
A17: 12
A18: 13
A19: 14
A20: 15
A21: 16
A22: 17
A23: 18
... A46: 41
E50: Total Advance collected | K50: =SUM(K6:K46) -> 25300000
E54: Fuel Sales for fuel station
A57: SN | B57: FDC# | C57: Loading Date | E57: Truck/Semi Trailor Plate No | F57: Origin | G57: Destination | H57: Type of Product | I57: QTY at 20 F | J57: Rate Per Litrs | K57: Total fuel Cost Amount (In Birr) (G= E*F)
D58: Driver's Name
A59: 1 | B59: 797987 | C59: 45503 | D59: Musa Adem | E59: 3-94462/28942 | F59: Djibouti | G59: Baeker | H59: AGO | I59: 45963 | J59: 84.3492 | K59: =I59*J59 -> 3876942.3
A60: 2 | B60: 814019 | C60: 45549 | D60: Musa Adem | E60: 3-94462/28942 | F60: Djibouti | G60: Baeker | H60: AGO | I60: 46001 | J60: 84.3492 | K60: =I60*J60 -> 3880147.5
A61: 3 | B61: 820817 | C61: 45570 | D61: Musa Adem | E61: 3-94462/28942 | F61: Djibouti | G61: Baeker | H61: AGO | I61: 46065 | J61: 84.3492 | K61: =I61*J61 -> 3885545.9
A62: 4 | B62: 836718 | C62: 45610 | D62: Getachew Alemshet | E62: 3-90951/27927 | F62: Djibouti | G62: Baeker | H62: AGO | I62: 46272 | J62: 90.9292 | K62: =I62*J62 -> 4207475.9
A63: 5 | B63: 842513 | C63: 45626 | D63: Getachew Alemshet | E63: 3-90951/27927 | F63: Djibouti | G63: Baeker | H63: AGO | I63: 46251 | J63: 90.9292 | K63: =I63*J63 -> 4205566.4
A64: 6 | F64: Djibouti | K64: =I64*J64 -> 0
A65: 7 | F65: Djibouti | K65: =I65*J65 -> 0
A66: 8 | F66: Djibouti | K66: =I66*J66 -> 0
A67: 9 | F67: Djibouti | K67: =I67*J67 -> 0
A68: 10 | F68: Djibouti | K68: =I68*J68 -> 0
A69: 11 | F69: Djibouti | K69: =I69*J69 -> 0
A70: 12 | F70: Djibouti | K70: =I70*J70 -> 0
A71: 13 | F71: Djibouti | K71: =I71*J71 -> 0
A72: 14 | F72: Djibouti | K72: =I72*J72 -> 0
A73: 15 | F73: Djibouti | K73: =I73*J73 -> 0
A74: 16 | F74: Djibouti | K74: =I74*J74 -> 0
A75: 17 | F75: Djibouti | K75: =I75*J75 -> 0
... A84: 26 | F84: Djibouti | K84: =I84*J84 -> 0
A85: total | K85: =SUM(K59:K84) -> 20055678
E91: Grand Total fuels sales | K91: =K85 -> 20055678
E93: Account Receivable(Payable ) | K93: =K50-K91 -> 5244321.9

Sheet Dansha(Wendem)
A2: Advance collected from fuel station :
A4: SN | B4: Date | C4: Bank | D4: Reference | E4: Description | L4: Amounts | N4: 110588.71 | O4: Transfer From Last year
A5: 1 | B5: 45556 | C5: CBE | D5: FT24265D9LX | E5: Advance Collection | L5: 4200000
A6: 2 | B6: 45579 | C6: CBE | D6: FT24288MTYY6 | E6: Advance Collection | L6: 467930
A7: 2 | B7: 45596 | C7: CBE | D7: FT243051DWQO | E7: Advance Collection | L7: 4200000
A8: 3 | B8: 45607 | C8: CBE | D8: FT243657VRLB | E8: Advance Collection | L8: 302410 | M8: NB | N8: 89100 | O8: Fuel From Station | P8: to Sintayehu
A9: 4 | B9: 45621 | C9: CBE | D9: FT24330LGTWG | E9: Advance Collection | L9: 3500000 | N9: 50000 | O9: Abel | P9: to Sintayehu
A10: 5 | B10: 45639 | C10: CBE | D10: FT243486R7DN | E10: Advance Collection | L10: 1000000
A11: 6 | B11: 45646 | C11: CBE | D11: FT24355FJSXB | E11: Advance Collection | L11: 151392
A12: 7 | B12: 45656 | C12: CBE | D12: FT243657VRLB | E12: Advance Collection | L12: 4000000
A13: 8
A14: 9
A15: 10
A16: 11
A17: 12
A18: 13
A19: 14
A20: 15
A21: 16
A22: 17
A23: 18
A24: 19
... A46: 41
E47: Total Advance collected | L47: =SUM(L5:L46) -> 17821732
E54: Fuel Sales for fuel station
A57: SN | B57: FDC# | C57: Loading Date | E57: Truck/Semi Trailor Plate No | F57: Origin | G57: Destination | H57: Type of Product | I57: QTY at 20 F | J57: Rate Per Litrs | K57: Rate Per Litrs | L57: Total fuel Cost Amount (In Birr) (G= E*F)
D58: Driver's Name
F59: Credit Transfer from Last year | G59: ast year | L59: 110588.71 | N59: 110588.71 | O59: Transfer from Last | P59: ast year
A60: 1 | B60: 820815 | C60: 45570 | D60: Sintayehu Esheta | E60: 3-91450/27736 | F60: Djibouti | G60: Dansha | H60: AGO | I60: 48110 | J60: 84.0592 | L60: =I60*J60 -> 4044088.1 | N60: 131810 | O60: 900 Fuel +50,000.00 | P60: Abel | Q60: 336,120 to Kumbi
A61: 2 | B61: 832406 | C61: 45600 | D61: Endalk Kbret | E61: 3-93865/29153 | F61: Djibouti | G61: Dansha | H61: AGO | I61: 48210 | J61: 90.6292 | L61: =I61*J61 -> 4369233.7 | N61: 302410 | O61: to Kumbi
A62: 3 | B62: 846854 | C62: 45639 | D62: Sintayehu Esheta | E62: 3-91450/27736 | F62: Djibouti | G62: Dansha | H62: AGO | I62: 48452 | J62: 90.6292 | L62: =I62*J62 -> 4391166 | N62: 139100 | O62: 900 Fuel +50,000.00
A63: 4 | B63: 854861 | C63: 45659 | D63: Endalk Kbret | E63: 3-93865/29153 | F63: Djibouti | G63: Dansha | H63: AGO | I63: 48324 | J63: 90.6292 | L63: =I63*J63 -> 4379565.5
A64: 5 | F64: Djibouti | L64: =I64*J64 -> 0
A65: 6 | F65: Djibouti | L65: =I65*J65 -> 0
A66: 7 | F66: Djibouti | L66: =I66*J66 -> 0
A67: 8 | F67: Djibouti | L67: =I67*J67 -> 0
A68: 9 | F68: Djibouti | L68: =I68*J68 -> 0
A69: 10 | F69: Djibouti | L69: =I69*J69 -> 0
A70: 11 | F70: Djibouti | L70: =I70*J70 -> 0
A71: 12 | F71: Djibouti | L71: =I71*J71 -> 0
A72: 13 | F72: Djibouti | L72: =I72*J72 -> 0
A73: 14 | F73: Djibouti | L73: =I73*J73 -> 0
A74: 15 | F74: Djibouti | L74: =I74*J74 -> 0
A75: 16 | F75: Djibouti | L75: =I75*J75 -> 0
A76: 17 | F76: Djibouti
A77: 18 | F77: Djibouti
A78: 19 | F78: Djibouti
A79: 20 | F79: Djibouti
A80: 21 | F80: Djibouti
A81: 22 | F81: Djibouti
A82: 23 | F82: Djibouti
A83: 24 | F83: Djibouti
A84: 25 | F84: Djibouti
A85: 26 | F85: Djibouti
A86: total | L86: =SUM(L59:L85) -> 17294642
E92: Grand Total fuels sales | L92: =L86 -> 17294642
E94: Account Receivable(Payable ) | L94: =L47-L92 -> 527089.99

Sheet Gonder Bikl Factory
B1: Gonder(Malte) Factory
A2: Advance collected from fuel station :
A4: SN | B4: Date | C4: Bank | D4: Reference | E4: Description | K4: Amounts
A5: 1 | B5: 45496 | C5: Abay | D5: 202FTRQ242050069 | E5: Advance Collection | K5: 4281600
A6: 2
A7: 2
A8: 3
A9: 4
A10: 5
A11: 6
A12: 7
A13: 8
A14: 9
A15: 10
A16: 11
A17: 12
... A45: 40
A46: 41 | E46: )
E50: Total Advance collected | K50: =SUM(K5:K46) -> 4281600
E54: Fuel Sales for fuel station
A57: SN | B57: FDC# | C57: Loading Date | E57: Truck/Semi Trailor Plate No | F57: Origin | G57: Destination | H57: Type of Product | I57: QTY at 20 F | J57: Rate Per Litrs | K57: Total fuel Cost Amount (In Birr) (G= E*F) | L57: New Price
D58: Driver's Name
A59: 1 | B59: 797574 | C59: 45507 | D59: Sintayehu Esheta | E59: 3-91450/27736 | F59: Djibouti | G59: Donder(Bikil | H59: HFO | I59: 48094 | J59: 71.36 | K59: =I59*J59 -> 3431987.8
A60: 2 | F60: Djibouti | K60: =I60*J60 -> 0 | L60: 104.83
A61: 3 | F61: Djibouti | K61: =I61*J61 -> 0
A62: 4 | F62: Djibouti | K62: =I62*J62 -> 0
A63: 5 | F63: Djibouti | K63: =I63*J63 -> 0
A64: 6 | F64: Djibouti | K64: =I64*J64 -> 0
A65: 7 | F65: Djibouti | K65: =I65*J65 -> 0
A66: 8 | F66: Djibouti | K66: =I66*J66 -> 0
A67: 9 | F67: Djibouti | K67: =I67*J67 -> 0
A68: 10 | F68: Djibouti | K68: =I68*J68 -> 0
A69: 11 | F69: Djibouti | K69: =I69*J69 -> 0
A70: 12 | F70: Djibouti | K70: =I70*J70 -> 0
A71: 13 | F71: Djibouti | K71: =I71*J71 -> 0
A72: 14 | F72: Djibouti | K72: =I72*J72 -> 0
... A84: 26 | F84: Djibouti | K84: =I84*J84 -> 0
A85: total | K85: =SUM(K59:K84) -> 3431987.8
E91: Grand Total fuels sales | K91: =K85 -> 3431987.8
E93: Account Receivable(Payable ) | K93: =K50-K91 -> 849612.16

Sheet Deposit From  Others
C1: Deposit From Other Componys | F1: panys
A2: Advance collected from fuel station :
A4: SN | B4: Date | C4: Bank | D4: Reference | E4: Description | K4: Amounts
A5: 1 | B5: 45533 | C5: CBE | D5: FT2424265FC3 | E5: Collected From Others(Baro Tesfaye Yideg) | K5: 2000000
A6: 2 | B6: 45538 | C6: CBE | D6: FT24247FFZ3L | E6: Collected From Others(Baro Tesfaye Yideg) | K6: 1200000
A7: 2 | B7: 45608 | C7: Awash | D7: 106412112416321988020 | E7: Collected From Others(Baro Tesfaye Yideg) | G7: Temesgen | H7: Yideg | K7: 1800000
A8: 3
A9: 4
A10: 5
A11: 6
A12: 7
A13: 8
A14: 9
A15: 10
A16: 11
A17: 12
A18: 13
A19: 14
... A45: 40
A46: 41 | E46: )
E50: Total Advance collected | K50: =SUM(K5:K46) -> 5000000
E54: Fuel Sales for fuel station
A57: SN | B57: FDC# | C57: Loading Date | E57: Truck/Semi Trailor Plate No | F57: Origin | G57: Destination | H57: Type of Product | I57: QTY at 20 F | J57: Rate Per Litrs | K57: Total fuel Cost Amount (In Birr) (G= E*F)
D58: Driver's Name | M58: 3434306.5
A59: 1 | M59: 3200000
A60: 2 | M60: =M58-M59 -> 234306.55
A61: 3 | F61: Djibouti | K61: =I61*J61 -> 0
A62: 4 | F62: Djibouti | K62: =I62*J62 -> 0
A63: 5 | F63: Djibouti | K63: =I63*J63 -> 0
A64: 6 | F64: Djibouti | K64: =I64*J64 -> 0
A65: 7 | F65: Djibouti | K65: =I65*J65 -> 0
A66: 8 | F66: Djibouti | K66: =I66*J66 -> 0
A67: 9 | F67: Djibouti | K67: =I67*J67 -> 0
A68: 10 | F68: Djibouti | K68: =I68*J68 -> 0
A69: 11 | F69: Djibouti | K69: =I69*J69 -> 0
A70: 12 | F70: Djibouti | K70: =I70*J70 -> 0
A71: 13 | F71: Djibouti | K71: =I71*J71 -> 0
A72: 14 | F72: Djibouti | K72: =I72*J72 -> 0
... A84: 26 | F84: Djibouti | K84: =I84*J84 -> 0
A85: total | K85: =SUM(K59:K84) -> 0
E91: Grand Total fuels sales | K91: =K85 -> 0
E93: Account Receivable(Payable ) | K93: =K50-K91 -> 5000000

Sheet Dansha(Tegegne)
A2: Advance collected from fuel station :
A4: SN | B4: Date | C4: Bank | D4: Reference | E4: Description | L4: Amounts
A5: 1
A6: 2
A7: 2
A8: 3
A9: 4
A10: 5
A11: 6
A12: 7
A13: 8
A14: 9
A15: 10
A16: 11
... A46: 41
E47: Total Advance collected | L47: =SUM(L5:L46) -> 0
E54: Fuel Sales for fuel station
A57: SN | B57: FDC# | C57: Loading Date | E57: Truck/Semi Trailor Plate No | F57: Origin | G57: Destination | H57: Type of Product | I57: QTY at 20 F | J57: Rate Per Litrs | K57: Rate Per Litrs | L57: Total fuel Cost Amount (In Birr) (G= E*F)
D58: Driver's Name
F59: Djibouti
A60: 1 | F60: Djibouti
A61: 2 | F61: Djibouti
A62: 3 | F62: Djibouti
A63: 4 | F63: Djibouti
A64: 5 | F64: Djibouti
A65: 6 | F65: Djibouti
A66: 7 | F66: Djibouti
A67: 8 | F67: Djibouti
A68: 9 | F68: Djibouti
A69: 10 | F69: Djibouti
A70: 11 | F70: Djibouti
A71: 12 | F71: Djibouti
... A85: 26 | F85: Djibouti
A86: total | L86: =SUM(L59:L85) -> 0
E92: Grand Total fuels sales | L92: =L86 -> 0
E94: Account Receivable(Payable ) | L94: =L47-L92 -> 0

Sheet Sheet1
G4: Fuel Costs -EPSE
C5: 2
C6: 3 | D6: FDC# | E6: Loading Date | G6: Truck/Semi Trailor Plate No | H6: Origin | I6: Destination | J6: Type of Product | K6: QTY at 20 F | L6: Fuel cost Per Litrs | M6: Total fuel Cost Amount (In Birr) (G= E*F) | R6: 3 | S6: FDC# | T6: Loading Date | V6: Truck/Semi Trailor Plate No | W6: Origin | X6: Destination | Y6: Type of Product | Z6: QTY at 20 F | AA6: Fuel cost Per Litrs | AB6: Total fuel Cost Amount (In Birr) (G= E*F)
C7: 4 | F7: Driver's Name | R7: 4 | U7: Driver's Name
C8: 5 | D8: 789278 | E8: 45481 | F8: Destalem Abreha | G8: 3-71435/21297 | H8: Djb | I8: Mito(Silta) | J8: MGR | K8: 46483 | L8: 71.6167 | M8: =K8*L8 -> 3328959.1 | R8: 1 | S8: 839955 | T8: 45620 | U8: Tsegay | V8: 3-93865/29153 | W8: Djb | X8: Dashen | Y8: LFO | Z8: 48516 | AA8: 93.5632 | AB8: =Z8*AA8 -> 4539312.2
C9: 6 | D9: 790007 | E9: 45482 | F9: Sintayehu Esheta | G9: 3-91450/27736 | H9: Djb | I9: Gesuba(Welaita | J9: MGR | K9: 47580 | L9: 71.6167 | M9: =K9*L9 -> 3407522.6
C10: 7 | D10: 790976 | E10: 45485 | F10: Musa Adem | G10: 3-94462/28942 | H10: Djb | I10: Mykadra | J10: AGO | K10: 45977 | L10: 76.5447 | M10: =K10*L10 -> 3519295.7
C11: 8 | D11: 791486 | E11: 45486 | F11: Hassen Mehamed | G11: 3-94456/28742 | H11: Djb | I11: Awash | J11: AGO | K11: 46047 | M11: =K11*L11 -> 0
C12: 9 | D12: 791850 | E12: 45486 | F12: Tsehaye G/medhn | G12: 3-93045/28723 | H12: Djb | I12: Awash | J12: AGO | K12: 45918 | M12: =K12*L12 -> 0
C13: 10 | D13: 791485 | E13: 45487 | F13: Tesfemariam Birhane | G13: 3-98387/29971 | H13: Djb | I13: Awash | J13: AGO | K13: 46792 | M13: =K13*L13 -> 0
C14: 11 | D14: 786564 | E14: 45487 | F14: Wedneh Bekele | G14: 3-93601/28714 | H14: Djb | I14: Batu(Coustc | J14: HFO | K14: 45946 | L14: 57.7473 | M14: =K14*L14 -> 2653257.4
C15: 12 | D15: 790976 | E15: 45493 | F15: Niguse Tadese | G15: 3-93449/28749 | H15: Djb | I15: Leha(Gofa) | J15: MGR | K15: 45667 | L15: 75.4077 | M15: =K15*L15 -> 3443643.4
C16: 13 | D16: 793663 | E16: 45493 | F16: Ayalneh Asefa | G16: 3-81046/24745 | H16: Djb | I16: Metu(Elibaboura | J16: AGO | K16: 50550 | L16: 76.5447 | M16: =K16*L16 -> 3869334.6
C17: 14 | D17: 796212 | E17: 45498 | F17: Tesfemariam Birhane | G17: 3-98387/29971 | H17: Djb | I17: Gesuba(Welaita | J17: AGO | K17: 46811 | L17: 76.5447 | M17: =K17*L17 -> 3583134
C18: 15 | D18: 796916 | E18: 45501 | F18: Getachew Alemshet | G18: 3-90951/27927 | H18: Djb | I18: Batu(Coustc | J18: HFO | K18: 45961 | L18: 57.7473 | M18: =K18*L18 -> 2654123.7
C19: 16 | D19: 797320 | E19: 45501 | F19: Destalem Abreha | G19: 3-71435/21297 | H19: Djb | I19: Dubti(Afar) | J19: AGO | K19: 46860 | L19: 76.5447 | M19: =K19*L19 -> 3586884.6
C20: 17 | D20: 797987 | E20: 45503 | F20: Musa Adem | G20: 3-94462/28942 | H20: Djb | I20: Baeker | J20: AGO | K20: 45963 | L20: 76.5447 | M20: =K20*L20 -> 3518224
C21: 18 | D21: 798914 | E21: 45504 | F21: Kasahun Tona | G21: 3-93024/28706 | H21: Djb | I21: Metu(Elibaboura | J21: MGR | K21: 45726 | L21: 75.4077 | M21: =K21*L21 -> 3448092.5
C22: 19 | D22: 797574 | E22: 45507 | F22: Sintayehu Esheta | G22: 3-91450/27736 | H22: Djb | I22: Gonder bikil F | J22: HFO | K22: 48094 | L22: 57.7473 | M22: =K22*L22 -> 2777298.6
C23: 20 | D23: 799506 | E23: 45510 | F23: Abebe Teka | G23: 3-94456/28742 | H23: Djb | I23: Gesuba(Welaita | J23: MGR | K23: 45780 | L23: 75.4077 | M23: =K23*L23 -> 3452164.5
C24: 21 | D24: 801261 | E24: 45512 | F24: Niguse Tadese | G24: 3-93449/28749 | H24: Djb | I24: Batu(Coustc | J24: HFO | K24: 45771 | L24: 57.7473 | M24: =K24*L24 -> 2643151.7
C25: 22 | D25: 802080 | E25: 45516 | F25: Teweldebrhan Gebrezgabi | G25: 3-93601/28714 | H25: Djb | I25: Mito(Silta) | J25: MGR | K25: 45688 | L25: 75.4077 | M25: =K25*L25 -> 3445227
... C29: 26 | D29: 805662 | E29: 45525 | F29: Teshome Tesfaye | G29: 3-93434/28741 | H29: Djb | I29: Metu(Elibaboura | J29: AGO | K29: 45948 | L29: 76.5447 | M29: =K29*L29 -> 3517075.9
C30: 27 | D30: 806442 | E30: 45526 | F30: Nigus Birhane | G30: 3-89959/27428 | H30: Djb | I30: Awash (Epse | J30: AGO | K30: 47253 | M30: =K30*L30 -> 0
C31: 28 | D31: 806904 | E31: 45527 | F31: Destalem Abreha | G31: 3-71435/21297 | H31: Djb | I31: Awash (Epse | J31: AGO | K31: 46854 | M31: =K31*L31 -> 0
C32: 29 | D32: 807109 | E32: 45528 | F32: Teweldebrhan Gebrezgabi | G32: 3-93601/28714 | H32: Djb | I32: Mito(Silta) | J32: AGO | K32: 45927 | L32: 76.5447 | M32: =K32*L32 -> 3515468.4
C33: 30 | D33: 805665 | E33: 45531 | F33: Getachew Alemshet | G33: 3-90951/27927 | H33: Djb | I33: Leha(Gofa) | J33: MGR | K33: 45833 | L33: 75.4077 | M33: =K33*L33 -> 3456161.1
C34: 31 | D34: 809553 | E34: 45535 | F34: Gebrezgabher Teweidebr | G34: 3-93024/28706 | H34: Djb | I34: Gesuba(Welaita) | J34: MGR | K34: 45892 | L34: 75.4077 | M34: =K34*L34 -> 3460610.2
C35: 32 | D35: 809183 | E35: 45535 | F35: Niguse Tadese | G35: 3-93449/28749 | H35: Djb | I35: Dashen(Gonder) | J35: LHF | K35: 46344 | L35: 58.9894 | M35: =K35*L35 -> 2733804.8
C36: 33 | D36: 772808 | E36: 45538 | F36: Endalk Kibret | G36: 3-93865/29153 | H36: Djb | I36: Awash (Epse | J36: AGO | K36: 48078 | M36: =K36*L36 -> 0
C37: 34 | D37: 810608 | E37: 45539 | F37: Abebe Teka | G37: 3-94456/28742 | H37: Djb | I37: Gesuba(Welaita | J37: AGO | K37: 46058 | L37: 76.5447 | M37: =K37*L37 -> 3525495.8
C38: 35 | D38: 811070 | E38: 45543 | F38: Andualem Demoz | G38: 3-90870/27584 | H38: Djb | I38: Metu(Elibaboura | J38: MGR | K38: 45431 | L38: 75.4077 | M38: =K38*L38 -> 3425847.2
C39: 36 | D39: 812527 | E39: 45544 | F39: Tesfemariam Birhane | G39: 3-98387/29971 | H39: Djb | I39: Awash (EPSE) | J39: AGO | K39: 46869 | M39: =K39*L39 -> 0
C40: 37 | D40: 812742 | E40: 45544 | F40: Nigus Birhane | G40: 3-89959/27428 | H40: Djb | I40: Awash (EPSE) | J40: AGO | K40: 47287 | M40: =K40*L40 -> 0
C41: 38 | D41: 812861 | E41: 45544 | F41: Destalem Abreha | G41: 3-71435/21297 | H41: Djb | I41: Awash (EPSE) | J41: AGO | K41: 46858 | M41: =K41*L41 -> 0
C42: 39 | D42: 813257 | E42: 45546 | F42: Weldekidan Hailu | G42: 3-98388/29973 | H42: Djb | I42: Leha(Gofa) | J42: AGO | K42: 46608 | L42: 76.5447 | M42: =K42*L42 -> 3567595.4
C43: 40 | D43: 811543 | E43: 45548 | F43: Teweldebrhan Gebrezgabi | G43: 3-93601/28714 | H43: Djb | I43: Mito(Silta) | J43: MGR | K43: 45598 | L43: 75.4077 | M43: =K43*L43 -> 3438440.3
C44: 41 | D44: 814019 | E44: 45549 | F44: Musa Adem | G44: 3-94462/28942 | H44: Djb | I44: Baeker | J44: AGO | K44: 46001 | L44: 76.5447 | M44: =K44*L44 -> 3521132.7
C45: 42 | D45: 816619 | E45: 45555 | F45: Teshome Tesfaye | G45: 3-93434/28741 | H45: Djb | I45: Batu(Coustc | J45: HFO | K45: 46036 | L45: 57.7473 | M45: =K45*L45 -> 2658454.7
C46: 43 | D46: 818517 | E46: 45560 | F46: Gebrezgabher Teweidebr | G46: 3-93024/28706 | H46: Djb | I46: Gesuba(Welaita | J46: MGR | K46: 45957 | L46: 75.4077 | M46: =K46*L46 -> 3465511.7
C47: 44 | D47: 818476 | E47: 45562 | F47: Abebe Teka | G47: 3-94456/28742 | H47: Djb | I47: Metu(Elibaboura | J47: AGO | K47: 46063 | L47: 76.5447 | M47: =K47*L47 -> 3525878.5
C48: 45 | D48: 819018 | E48: 45563 | F48: Teweldebrhan Gebrezgabi | G48: 3-93601/28714 | H48: Djb | I48: Gesuba(Welaita | J48: AGO | K48: 45918 | L48: 76.5447 | M48: =K48*L48 -> 3514779.5
C49: 46 | D49: 820815 | E49: 45570 | F49: Sintayehu Esheta | G49: 3-91450/27736 | H49: Djb | I49: Dansha | J49: AGO | K49: 48110 | L49: 76.5447 | M49: =K49*L49 -> 3682565.5
C50: 47 | D50: 820817 | E50: 45570 | F50: Musa Adem | G50: 3-94462/28942 | H50: Djb | I50: Baeker | J50: AGO | K50: 46065 | L50: 76.5447 | M50: =K50*L50 -> 3526031.6
C51: 48 | D51: 821685 | E51: 45571 | F51: Teshome Tesfaye | G51: 3-93434/28741 | H51: Djb | I51: Mito(Silta) | J51: AGO | K51: 45905 | L51: 76.5447 | M51: =K51*L51 -> 3513784.5
C52: 49 | D52: 821691 | E52: 45572 | F52: Endalk Kibret | G52: 3-93865/29153 | H52: Djb | I52: Dashne(Gonder) | J52: LFO | K52: 48448 | L52: 65.89 | M52: =K52*L52 -> 3192238.7
C53: 50 | D53: 821257 | E53: 45574 | F53: Gebrezgabher Teweidebr | G53: 3-93024/28706 | H53: Djb | I53: Metu(Elibaboura | J53: MGR | K53: 45867 | L53: 83.8135 | M53: =K53*L53 -> 3844273.8
... C59: 56 | D59: 829003 | E59: 45590 | F59: Musa Adem | G59: 3-94462/28942 | H59: Djb | I59: Dashne(Gonder) | J59: LFO | K59: 46470 | L59: 93.5632 | M59: =K59*L59 -> 4347881.9
C60: 57 | D60: 829279 | E60: 45590 | F60: Gebrezgabher Teweidebr | G60: 3-93024/28706 | H60: Djb | I60: Awash (EPSE) | J60: AGO | K60: 46250 | M60: =K60*L60 -> 0
C61: 58 | D61: 829745 | E61: 45591 | F61: Teweldebrhan Gebrezgabi | G61: 3-93601/28714 | H61: Djb | I61: Mito(Silta) | J61: AGO | K61: 46082 | L61: 82.9506 | M61: =K61*L61 -> 3822529.5
C62: 59 | D62: 827682 | E62: 45592 | F62: Teshome Tesfaye | G62: 3-93434/28741 | H62: Djb | I62: Metu(Elibaboura | J62: MGR | K62: 45862 | L62: 83.8135 | M62: =K62*L62 -> 3843854.7
C63: 60 | D63: 827679 | E63: 45593 | F63: Ayalneh Asefa | G63: 3-81046/24745 | H63: Djb | I63: Awash (EPSE) | J63: AGO | K63: 50780 | M63: =K63*L63 -> 0
C64: 61 | D64: 832406 | E64: 45600 | F64: Endalk Kibret | G64: 3-93865/29153 | H64: Djb | I64: Dansha(Wendem | J64: AGO | K64: 48210 | L64: 82.9506 | M64: =K64*L64 -> 3999048.4
C65: 62 | D65: 833747 | E65: 45604 | F65: Musa Adem | G65: 3-94462/28942 | H65: Djb | I65: Dashne(Gonder) | J65: LFO | K65: 46431 | L65: 93.5632 | M65: =K65*L65 -> 4344232.9
C66: 63 | D66: 834606 | E66: 45605 | F66: Weldekidan Hailu | G66: 3-98388/29973 | H66: Djb | I66: Leha(Gofa) | J66: AGO | K66: 46552 | L66: 82.9506 | M66: =K66*L66 -> 3861516.3
C67: 64 | D67: 834611 | E67: 45607 | F67: Sintayehu Esheta | G67: 3-91450/27736 | H67: Djb | I67: Adebay | J67: AGO | K67: 48475 | L67: 82.9506 | M67: =K67*L67 -> 4021030.3
C68: 65 | D68: 833746 | E68: 45608 | F68: Gebrezgabher Teweidebr | G68: 3-93024/28706 | H68: Djb | I68: Gesuba(Welaita | J68: MGR | K68: 46127 | L68: 83.8135 | M68: =K68*L68 -> 3866065.3
C69: 66 | D69: 836718 | E69: 45610 | F69: Getachew Alemshet | G69: 3-90951/27927 | H69: Djb | I69: Baeker | J69: AGO | K69: 46272 | L69: 82.9506 | M69: =K69*L69 -> 3838290.2
C70: 67 | D70: 837125 | E70: 45612 | F70: Birhane G/ezgabher | G70: 3-93573/28711 | H70: Djb | I70: Welaita Sodo (Depot) | J70: AGO | K70: 46269 | M70: 0
C71: 68 | D71: 837311 | E71: 45615 | F71: Teweldebrhan Gebrezgabi | G71: 3-93601/28714 | H71: Djb | I71: Metu(Elibaboura | J71: AGO | K71: 46127 | L71: 82.9506 | M71: =K71*L71 -> 3826262.3
C72: 69 | D72: 838248 | E72: 45616 | F72: Teshome Tesfaye | G72: 3-93434/28741 | H72: Djb | I72: Mito(Silta) | J72: AGO | K72: 46204 | L72: 82.9506 | M72: =K72*L72 -> 3832649.5
C73: 70 | D73: 838249 | E73: 45618 | F73: Nigus Birhane | G73: 3-89959/27428 | H73: Djb | I73: Adebay | J73: MGR | K73: 47340 | L73: 83.8135 | M73: =K73*L73 -> 3967731.1
C74: 71 | D74: 839959 | F74: Musa Adem | G74: 3-94462/28942 | H74: Djb | I74: S.Humera | J74: AGO | K74: 46264 | L74: 82.9506 | M74: =K74*L74 -> 3837626.6
C75: 72 | D75: 839955 | F75: Endalk Kibret | G75: 3-93865/29153 | H75: Djb | I75: Dashne(Gonder) | J75: LFO | K75: 48516 | L75: 93.5632 | M75: =K75*L75 -> 4539312.2
C76: 73 | H76: Djb | M76: =K76*L76 -> 0
C77: 74 | H77: Djb | M77: =K77*L77 -> 0
C78: 75 | H78: Djb | M78: =K78*L78 -> 0
C79: 76 | H79: Djb | M79: =K79*L79 -> 0
C80: 77 | H80: Djb | M80: =K80*L80 -> 0
C81: 78 | H81: Djb | M81: =K81*L81 -> 0
C82: 79 | H82: Djb | M82: =K82*L82 -> 0
C83: 80 | H83: Djb | M83: =K83*L83 -> 0
C84: 81 | H84: Djb | M84: =K84*L84 -> 0
C85: 82 | H85: Djb | M85: =K85*L85 -> 0
C86: 83 | H86: Djb | M86: =K86*L86 -> 0
C87: 84 | H87: Djb | M87: =K87*L87 -> 0
C88: 85 | H88: Djb | M88: =K88*L88 -> 0
M89: =SUM(M8:M88) -> 2.0067403e+08
